meebro/__init__.py
meebro/build.py
meebro/config.py
meebro-2.0.19.dist-info/METADATA
meebro-2.0.19.dist-info/WHEEL
meebro-2.0.19.dist-info/licenses/LICENSE
meebro-2.0.19.dist-info/RECORD
