Metadata-Version: 2.4
Name: meebro
Version: 2.0.19
Summary: A small example package
Author-email: Example Author <author@example.com>
License-Expression: MIT
License-File: LICENSE
Classifier: Operating System :: OS Independent
Classifier: Programming Language :: Python :: 3
Requires-Python: >=3.9
Requires-Dist: cryptography
